sigplot/__init__.py
sigplot/correlation.py
sigplot/sinusoids.py
sigplot-0.0.5.dist-info/LICENSE.txt
sigplot-0.0.5.dist-info/METADATA
sigplot-0.0.5.dist-info/WHEEL
sigplot-0.0.5.dist-info/top_level.txt
sigplot-0.0.5.dist-info/RECORD
